mutar/__init__.py
mutar/_version.py
mutar/estimators.py
mutar/otfunctions.py
mutar/solver_mtw_cd.cpython-36m-darwin.so
mutar/solvers.py
mutar/utils.py
mutar/tests/__init__.py
mutar/tests/conftest.py
mutar/tests/test_dirty.py
mutar/tests/test_indlasso.py
mutar/tests/test_mll.py
mutar/tests/test_mtw.py
mutar/tests/test_ot.py
mutar/tests/test_warnings.py
mutar-0.0.1.dist-info/LICENSE
mutar-0.0.1.dist-info/METADATA
mutar-0.0.1.dist-info/WHEEL
mutar-0.0.1.dist-info/top_level.txt
mutar-0.0.1.dist-info/RECORD
